plugs_ariadne_jwt/__init__.py
plugs_ariadne_jwt/apps.py
plugs_ariadne_jwt/decorators.py
plugs_ariadne_jwt/exceptions.py
plugs_ariadne_jwt/middleware.py
plugs_ariadne_jwt/models.py
plugs_ariadne_jwt/settings.py
plugs_ariadne_jwt/urls.py
plugs_ariadne_jwt/utils.py
plugs_ariadne_jwt/views.py
plugs_ariadne_jwt-0.3.0.dist-info/AUTHORS.rst
plugs_ariadne_jwt-0.3.0.dist-info/LICENSE
plugs_ariadne_jwt-0.3.0.dist-info/METADATA
plugs_ariadne_jwt-0.3.0.dist-info/WHEEL
plugs_ariadne_jwt-0.3.0.dist-info/top_level.txt
plugs_ariadne_jwt-0.3.0.dist-info/RECORD
