Metadata-Version: 2.1
Name: plugs-ariadne-jwt
Version: 0.3.0
Summary: Your project description goes here
Home-page: https://github.com/ricardolobo/plugs-ariadne-jwt
Author: Ricardo Lobo
Author-email: ricardolobo@solo.com.pt
License: MIT
Keywords: plugs-ariadne-jwt
Platform: UNKNOWN
Classifier: Development Status :: 3 - Alpha
Classifier: Framework :: Django :: 2.0
Classifier: Intended Audience :: Developers
Classifier: License :: OSI Approved :: BSD License
Classifier: Natural Language :: English
Classifier: Programming Language :: Python :: 2
Classifier: Programming Language :: Python :: 2.7
Classifier: Programming Language :: Python :: 3
Classifier: Programming Language :: Python :: 3.4
Classifier: Programming Language :: Python :: 3.5
Classifier: Programming Language :: Python :: 3.6
